{"is_source_file": true, "format": "CSS", "description": "Styles for the Tic Tac Toe frontend application, defining layout, color scheme, and responsive design.", "external_files": [], "external_methods": [], "published": [], "classes": [{"name": "App", "description": "Main styling for the App component including layout and background properties."}, {"name": "game-container", "description": "Styles for the game container that centralizes the content with padding."}, {"name": "game-title", "description": "Styles for the title of the game, including color and font size."}, {"name": "mode-button", "description": "Styles for the buttons that select the game mode, including active state."}, {"name": "status", "description": "Styles for the display status in the game, distinguishing it with color."}, {"name": "game-board", "description": "Styles that define the layout of the game board using grid properties."}, {"name": "square", "description": "Styles for each square in the Tic Tac Toe grid, including hover and filled states."}, {"name": "reset-button", "description": "Styles for the reset button, including hover effects."}], "methods": [], "calls": [], "search-terms": ["Tic Tac Toe", "game styles", "frontend CSS", "responsive design"], "state": 2, "file_id": 5, "knowledge_revision": 34, "git_revision": "045f0f89fd12d9306e24b39906009b203a015d6a", "revision_history": [{"22": "48fa772236205ac8ac66376461f06d2ebcff73a4"}, {"33": "48fa772236205ac8ac66376461f06d2ebcff73a4"}, {"34": "045f0f89fd12d9306e24b39906009b203a015d6a"}], "hash": "1360fe8a5f88b3b6e844de6297076f23", "format-version": 4, "code-base-name": "tic_tac_toe_frontend", "filename": "tic_tac_toe_frontend/src/App.css"}